{
  "$schema": "https://developer.microsoft.com/json-schemas/fabric/item/report/definition/visualContainer/2.2.0/schema.json",
  "name": "77fecd0ca31d02b98796",
  "position": {
    "x": 28.975609756097562,
    "y": 164.19512195121951,
    "z": 12000,
    "height": 23.707317073170731,
    "width": 312.58536585365857,
    "tabOrder": 9000
  },
  "visual": {
    "visualType": "textbox",
    "visualContainerObjects": {
      "title": [
        {
          "properties": {
            "show": {
              "expr": {
                "Literal": {
                  "Value": "true"
                }
              }
            },
            "text": {
              "expr": {
                "Literal": {
                  "Value": "'Modernisation des services'"
                }
              }
            },
            "heading": {
              "expr": {
                "Literal": {
                  "Value": "'Heading2'"
                }
              }
            },
            "fontSize": {
              "expr": {
                "Literal": {
                  "Value": "20D"
                }
              }
            }
          }
        }
      ],
      "background": [
        {
          "properties": {
            "show": {
              "expr": {
                "Literal": {
                  "Value": "false"
                }
              }
            }
          }
        }
      ]
    },
    "drillFilterOtherVisuals": true
  }
}